auto_i18n-1.6.4.dist-info/METADATA
auto_i18n-1.6.4.dist-info/WHEEL
auto_i18n-1.6.4.dist-info/entry_points.txt
auto_i18n-1.6.4.dist-info/licenses/LICENSE
auto_i18n/__init__.py
auto_i18n/cli.py
auto_i18n/config.py
auto_i18n/export.py
auto_i18n/extract.py
auto_i18n/gpt.py
auto_i18n/i18n/__init__.py
auto_i18n/i18n/en_US.yaml
auto_i18n/i18n/zh_CN.yaml
auto_i18n/io.py
auto_i18n/translate.py
auto_i18n/utils/__init__.py
auto_i18n/utils/echo.py
auto_i18n/utils/object.py
auto_i18n/utils/string.py
auto_i18n-1.6.4.dist-info/RECORD
