Metadata-Version: 2.1
Name: auto-i18n
Version: 1.6.4
Author-Email: frostime <frostime@foxmail.com>
License: MIT
Requires-Python: >=3.9
Requires-Dist: Click>=8.1.7
Requires-Dist: pyyaml>=6.0.2
Requires-Dist: requests>=2.32.3
